digplexq/__init__.py
digplexq/_version.py
digplexq/auxiliary_functions.py
digplexq/digraph_based_complexes.py
digplexq/directed_q_analysis.py
digplexq/discrete_curvatures.py
digplexq/discrete_morse_theory.py
digplexq/persistent_homology.py
digplexq/random_digraphs.py
digplexq/simplicial_neural_networks.py
digplexq/simplicial_statistics.py
digplexq/simplicial_weights.py
digplexq/spectrum_based_simplicial_measures.py
digplexq/structure_based_simplicial_distances.py
digplexq/structure_based_simplicial_measures.py
digplexq/substructure_enumeration.py
digplexq/utils.py
digplexq-0.0.7.dist-info/LICENSE.txt
digplexq-0.0.7.dist-info/METADATA
digplexq-0.0.7.dist-info/WHEEL
digplexq-0.0.7.dist-info/top_level.txt
digplexq-0.0.7.dist-info/RECORD
